progenomes/__init__.py
progenomes/download.py
progenomes/view.py
progenomes/cli/__init__.py
progenomes/cli/progenomes.py
progenomes-0.2.0.dist-info/licenses/LICENSE
tests/integration/test_cli_integration.py
tests/unit/test_download.py
tests/unit/test_view.py
progenomes-0.2.0.dist-info/METADATA
progenomes-0.2.0.dist-info/WHEEL
progenomes-0.2.0.dist-info/entry_points.txt
progenomes-0.2.0.dist-info/top_level.txt
progenomes-0.2.0.dist-info/RECORD
