Metadata-Version: 2.4
Name: proGenomes
Version: 0.2.0
Summary: A proGenomes command-line tool for interacting with bacterial and archeal genomes.
Author-email: proGenomes Development Team <luispedro@big-data-biology.org>
Maintainer-email: Alexandre Areias Castro <alexandre@big-data-biology.org>
License-Expression: MIT
Project-URL: Homepage, https://github.com/BigDataBiology/progenomes
Project-URL: Bug Reports, https://github.com/BigDataBiology/progenomes/issues
Project-URL: Source, https://github.com/BigDataBiology/progenomes
Keywords: bioinformatics,microbiology,metagenomics
Classifier: Development Status :: 3 - Alpha
Classifier: Topic :: Scientific/Engineering :: Bio-Informatics
Classifier: Topic :: Software Development :: Libraries :: Python Modules
Classifier: Topic :: Software Development :: Build Tools
Classifier: Intended Audience :: Science/Research
Classifier: Intended Audience :: Education
Classifier: Intended Audience :: Healthcare Industry
Classifier: Programming Language :: Python :: 3.9
Classifier: Programming Language :: Python :: 3.10
Classifier: Programming Language :: Python :: 3.11
Classifier: Programming Language :: Python :: 3.12
Classifier: Programming Language :: Python :: 3.13
Classifier: Operating System :: OS Independent
Classifier: Natural Language :: English
Requires-Python: >=3.9
License-File: LICENSE
Requires-Dist: polars
Requires-Dist: pandas
Requires-Dist: tqdm
Requires-Dist: pyarrow
Provides-Extra: dev
Requires-Dist: pytest; extra == "dev"
Dynamic: license-file
